invalid_search/__init__.py
invalid_search-1.0.4.dist-info/METADATA
invalid_search-1.0.4.dist-info/WHEEL
invalid_search-1.0.4.dist-info/top_level.txt
invalid_search-1.0.4.dist-info/RECORD
