Metadata-Version: 2.4
Name: invalid_search
Version: 1.0.4
Summary: Universal Phone Number Search Tool
Author-email: Ayush <pagals1818@gmail.com>
Requires-Python: >=3.8
Requires-Dist: httpx
